asgard_controllino/__init__.py
asgard_controllino/controls.py
ASGARD_Controllino-0.1.1.dist-info/METADATA
ASGARD_Controllino-0.1.1.dist-info/WHEEL
ASGARD_Controllino-0.1.1.dist-info/top_level.txt
ASGARD_Controllino-0.1.1.dist-info/RECORD
